{
	"menus":[
		{
			"icon":"icon-sys",
			"menuid":7,
			"menuname":"产品管理",
			"menus":[
				{
					"icon":"icon-sys",
					"menuid":18,
					"menuname":"附加种类配置<br>TypediversAnnextype",
					"url":"td_annex?lang=zh_CN"
				},
				{
					"icon":"icon-sys",
					"menuid":18,
					"menuname":"属性种类配置<br>TypediversAttributetype",
					"url":"td_attrs"
				},
				{
					"icon":"icon-sys",
					"menuid":9,
					"menuname":"型号种类配置<br>TypediversModeltype",
					"url":"td_modeltype"
				},
				{
					"icon":"icon-sys",
					"menuid":9,
					"menuname":"方案种类配置<br>TypediversPropositiontype",
					"url":"td_proposition"
				},
				{
					"icon":"icon-sys",
					"menuid":9,
					"menuname":"属性管理<br>PdtAttribute",
					"url":"attrs"
				}
				,
				{
					"icon":"icon-sys",
					"menuid":9,
					"menuname":"组件配置<br>PdtComponent",
					"url":"component"
				},
				{
					"icon":"icon-sys",
					"menuid":9,
					"menuname":"值管理<br>PdtElement",
					"url":"element"
				},
				{
					"icon":"icon-sys",
					"menuid":9,
					"menuname":"型号管理<br>PdtModel",
					"url":"model"
				},
				{
					"icon":"icon-sys",
					"menuid":9,
					"menuname":"方案管理<br>PdtProposition",
					"url":"proposition"
				}
			]
		}
		,
		{
			"icon":"icon-sys",
			"menuid":1,
			"menuname":"系统管理",
			"menus":[
				{
					"icon":"icon-sys",
					"menuid":3,
					"menuname":"系统资源监控",
					"url":"http://www.baidu.com"
				},
				{
					"icon":"icon-sys",
					"menuid":2,
					"menuname":"系统运行状态",
					"url":"http://www.baidu.com"
				},
				{
					"icon":"icon-sys",
					"menuid":3,
					"menuname":"操作日志",
					"url":"http://www.baidu.com"
				},
				{
					"icon":"icon-sys",
					"menuid":3,
					"menuname":"系统日志",
					"url":"http://www.baidu.com"
				}
				
			]
			
		},
		{
			"icon":"icon-sys",
			"menuid":1,
			"menuname":"权限管理",
			"menus":[
				{
					"icon":"icon-sys",
					"menuid":3,
					"menuname":"分组管理",
					"url":"http://www.baidu.com"
				},
				{
					"icon":"icon-sys",
					"menuid":2,
					"menuname":"角色管理",
					"url":"http://www.baidu.com"
				},
				{
					"icon":"icon-sys",
					"menuid":3,
					"menuname":"账户管理",
					"url":"http://www.baidu.com"
				},
				{
					"icon":"icon-sys",
					"menuid":3,
					"menuname":"资源管理",
					"url":"http://www.baidu.com"
				}
				
			]
			
		}
		
	]
}